{
  "posts": [
    { "id": 1,
     "title": "How to make .." ,
     "slug": "Lorem ipsum dolor sit amet, consectetur adipiscing elit, sed do eiusmod tempor incididunt ut labore et dolore magna aliqua. Ut enim ad minim veniam, quis nostrud exercitation ullamco laboris nisi ut aliquip ex ea commodo consequat. Duis aute irure dolor in reprehenderit in voluptate velit esse cillum dolore eu fugiat nulla pariatur. Excepteur sint occaecat cupidatat non proident, sunt in culpa qui officia deserunt mollit anim id est laborum", 
     "comments" : [
          { "id": 1, 
            "body": "wow it's great!"
           },
          {
            "id": 2,
            "body": "Wow!" 
          },
           { 
             "id": 3,
             "body": "It's cool!"
           }
     ]
    },
    { "id": 2, 
     "title": "Why you should.." ,
     "slug": "Lorem ipsum dolor sit amet, consectetur adipiscing elit, sed do eiusmod tempor incididunt ut labore et dolore magna aliqua. Ut enim ad minim veniam, quis nostrud exercitation ullamco laboris nisi ut aliquip ex ea commodo consequat. Duis aute irure dolor in reprehenderit in voluptate velit esse cillum dolore eu fugiat nulla pariatur. Excepteur sint occaecat cupidatat non proident, sunt in culpa qui officia deserunt mollit anim id est laborum2",
        "comments" : [
          { "id": 1, 
            "body": "wow it's great!"
           },
          {
            "id": 2,
            "body": "Wow!" 
          },
           { 
             "id": 3,
             "body": "It's cool!"
           },
           { 
             "id": 4,
             "body": "It's cool!"
           }
     ]
    },
    { 
      "id": 3, 
     "title": "Dont do and Do this.." ,
     "slug": "Lorem ipsum dolor sit amet, consectetur adipiscing elit, sed do eiusmod tempor incididunt ut labore et dolore magna aliqua. Ut enim ad minim veniam, quis nostrud exercitation ullamco laboris nisi ut aliquip ex ea commodo consequat. Duis aute irure dolor in reprehenderit in voluptate velit esse cillum dolore eu fugiat nulla pariatur. Excepteur sint occaecat cupidatat non proident, sunt in culpa qui officia deserunt mollit anim id est laborum",
     "comments" : [{ "id": 1, 
            "body": "wow it's great!"
           }]
    }
  ]
}
